src/__init__.py
src/config.py
src/container.py
src/main.py
src/application/__init__.py
src/application/services/__init__.py
src/application/services/contact.py
src/application/services/deal.py
src/domain/__init__.py
src/domain/bitrix_types.py
src/domain/entities/__init__.py
src/domain/entities/base_entity.py
src/domain/entities/contact.py
src/domain/entities/deal.py
src/domain/entities/smart_process.py
src/domain/interfaces/__init__.py
src/domain/interfaces/base_repository.py
src/infrastructure/__init__.py
src/infrastructure/ioc.py
src/infrastructure/bitrix/__init__.py
src/infrastructure/bitrix/bitrix_contact_repository.py
src/infrastructure/bitrix/bitrix_deal_repository.py
src/infrastructure/bitrix/repository_factory.py
src/infrastructure/bitrix/mixins/__init__.py
src/infrastructure/bitrix/mixins/base.py
src/infrastructure/bitrix/mixins/batch_operations.py
src/infrastructure/bitrix/mixins/filter_builder.py
src/infrastructure/bitrix/mixins/pagination.py
src/infrastructure/bitrix/mixins/read.py
src/infrastructure/bitrix/mixins/relationship.py
src/infrastructure/bitrix/mixins/write.py
src/infrastructure/logging/__init__.py
src/infrastructure/logging/logger.py
src/infrastructure/mcp/server.py
src/infrastructure/mcp/handlers/__init__.py
src/infrastructure/mcp/handlers/contact.py
src/infrastructure/mcp/handlers/deal.py
src/presentation/mcp.py
bitrix24_mcp-1.0.1.dist-info/METADATA
bitrix24_mcp-1.0.1.dist-info/WHEEL
bitrix24_mcp-1.0.1.dist-info/entry_points.txt
bitrix24_mcp-1.0.1.dist-info/licenses/LICENSE
bitrix24_mcp-1.0.1.dist-info/RECORD
