Metadata-Version: 2.4
Name: bitrix24-mcp
Version: 1.0.1
Summary: MCP server for interacting with Bitrix24 using natural language and AI dialogues to get data, perform actions, and manage the system.
License-File: LICENSE
Requires-Python: >=3.12
Requires-Dist: dishka>=1.5.3
Requires-Dist: fast-bitrix24>=1.8.4
Requires-Dist: mcp[cli]>=1.4.1
Requires-Dist: structlog>=25.2.0
